Workbook

Sheet CAPEX
A1: Cost factors
A2: Equipment erection | B2: fer | C2: 0.3
A3: Piping | B3: fp | C3: 0.8
A4: Instrumentation and control | B4: fi | C4: 0.3
A5: Electrical | B5: fel | C5: 0.2
A6: Civil | B6: fc | C6: 0.3
A7: Structures and buildings | B7: fs | C7: 0.2
A8: Lagging and paint | B8: fl | C8: 0.1
A9: Material factor for 304 SS | B9: fm | C9: 1.3
A12: Equipment | B12: Equipment approximated as | C12: Dimension needed | D12: Value | E12: a | F12: b | G12: n | H12: Purchased Cost (Ce,i,a) | J12: Equipment | K12: Internal diameter (m) | L12: h (m) | M12: External diameter (m) | N12: Area for shell (m2) | O12: Volume | P12: Density (kg/m3) | Q12: Shell mass (kg)
A13: Compressors | J13: POX | K13: 1.524 | L13: 5.334 | M13: =K13+0.0254 -> 1.5494 | N13: =PI()*(M13*M13-K13*K13)/4 -> 0.061311605 | O13: =N13*L13 -> 0.3270361 | P13: 8000 | Q13: =P13*O13 -> 2616.2888
A14: K-100 | B14: Centrifugal compressor | C14: Power, kW | D14: 1757.5948 | E14: 580000 | F14: 20000 | G14: 0.6 | H14: =(E14+(F14*(D14^G14)))/1000000 -> 2.3500326 | J14: V-100 | K14: 1.524 | L14: 5.334 | M14: =K14+0.0254 -> 1.5494 | N14: =PI()*(M14*M14-K14*K14)/4 -> 0.061311605 | O14: =N14*L14 -> 0.3270361 | P14: 8000 | Q14: =P14*O14 -> 2616.2888
A15: K-101 | B15: Centrifugal compressor | C15: Power, kW | D15: 1897.9966 | E15: 580000 | F15: 20000 | G15: 0.6 | H15: =(E15+(F15*(D15^G15)))/1000000 -> 2.4335626 | J15: V-101 | K15: 0.6096 | L15: 3.3528 | M15: =K15+0.0254 -> 0.635 | N15: =PI()*(M15*M15-K15*K15)/4 -> 0.024828666 | O15: =N15*L15 -> 0.083245553 | P15: 8000 | Q15: =P15*O15 -> 665.96442
A16: K-102 | B16: Centrifugal compressor | C16: Power, kW | D16: 1891.341 | E16: 580000 | F16: 20000 | G16: 0.6 | H16: =(E16+(F16*(D16^G16)))/1000000 -> 2.42966 | J16: V-102 | K16: 3.2004 | L16: 11.2014 | M16: =K16+0.0254 -> 3.2258 | N16: =PI()*(M16*M16-K16*K16)/4 -> 0.12819699 | O16: =N16*L16 -> 1.4359858 | P16: 8000 | Q16: =P16*O16 -> 11487.886
A17: K-103 | B17: Centrifugal compressor | C17: Power, kW | D17: 1291.6366 | E17: 580000 | F17: 20000 | G17: 0.6 | H17: =(E17+(F17*(D17^G17)))/1000000 -> 2.0513439 | J17: V-103 | K17: 1.0668 | L17: 5.8674 | M17: =K17+0.0254 -> 1.0922 | N17: =PI()*(M17*M17-K17*K17)/4 -> 0.043070136 | O17: =N17*L17 -> 0.25270971 | P17: 8000 | Q17: =P17*O17 -> 2021.6777
A18: K-104 | B18: Centrifugal compressor | C18: Power, kW | D18: 112.83663 | E18: 580000 | F18: 20000 | G18: 0.6 | H18: =(E18+(F18*(D18^G18)))/1000000 -> 0.92080037 | J18: V-104 | K18: 0.3048 | L18: 1.6764 | M18: =K18+0.0254 -> 0.3302 | N18: =PI()*(M18*M18-K18*K18)/4 -> 0.012667687 | O18: =N18*L18 -> 0.02123611 | P18: 8000 | Q18: =P18*O18 -> 169.88888
A19: K-105 | B19: Centrifugal compressor | C19: Power, kW | D19: 31.729199 | E19: 580000 | F19: 20000 | G19: 0.6 | H19: =(E19+(F19*(D19^G19)))/1000000 -> 0.73918622 | J19: V-105 | K19: 1.3716 | L19: 7.5438 | M19: =K19+0.0254 -> 1.397 | N19: =PI()*(M19*M19-K19*K19)/4 -> 0.055231115 | O19: =N19*L19 -> 0.41665249 | P19: 8000 | Q19: =P19*O19 -> 3333.2199
A20: K-106 | B20: Centrifugal compressor | C20: Power, kW | D20: 1.8582964 | E20: 580000 | F20: 20000 | G20: 0.6 | H20: =(E20+(F20*(D20^G20)))/1000000 -> 0.60900674 | J20: V-106 | K20: 0.762 | L20: 2.667 | M20: =K20+0.0254 -> 0.7874 | N20: =PI()*(M20*M20-K20*K20)/4 -> 0.030909156 | O20: =N20*L20 -> 0.08243472 | P20: 8000 | Q20: =P20*O20 -> 659.47776
A21: K-107 | B21: Centrifugal compressor | C21: Power, kW | D21: 1.9812222 | E21: 580000 | F21: 20000 | G21: 0.6 | H21: =(E21+(F21*(D21^G21)))/1000000 -> 0.61014324 | J21: V-107 | K21: 1.3716 | L21: 7.5438 | M21: =K21+0.0254 -> 1.397 | N21: =PI()*(M21*M21-K21*K21)/4 -> 0.055231115 | O21: =N21*L21 -> 0.41665249 | P21: 8000 | Q21: =P21*O21 -> 3333.2199
A22: K-108 | B22: Centrifugal compressor | C22: Power, kW | D22: 2.0742247 | E22: 580000 | F22: 20000 | G22: 0.6 | H22: =(E22+(F22*(D22^G22)))/1000000 -> 0.61098443 | J22: T-100 | K22: 1.416 | L22: =0.6096*10 -> 6.096 | M22: =K22+0.0254 -> 1.4414 | N22: =PI()*(M22*M22-K22*K22)/4 -> 0.057002596 | O22: =N22*L22 -> 0.34748783 | P22: 8000 | Q22: =P22*O22 -> 2779.9026
A23: K-109 | B23: Centrifugal compressor | C23: Power, kW | D23: 1.4434992 | E23: 580000 | F23: 20000 | G23: 0.6 | H23: =(E23+(F23*(D23^G23)))/1000000 -> 0.60492757 | J23: T-101 | K23: 1.642 | L23: =0.6096*2 -> 1.2192 | M23: =K23+0.0254 -> 1.6674 | N23: =PI()*(M23*M23-K23*K23)/4 -> 0.066019596 | O23: =N23*L23 -> 0.080491091 | P23: 8000 | Q23: =P23*O23 -> 643.92873
A24: K-110 | B24: Centrifugal compressor | C24: Power, kW | D24: 867.14823 | E24: 580000 | F24: 20000 | G24: 0.6 | H24: =(E24+(F24*(D24^G24)))/1000000 -> 1.7384732 | J24: T-102 | K24: 1.129 | L24: 0.6096 | M24: =K24+0.0254 -> 1.1544 | N24: =PI()*(M24*M24-K24*K24)/4 -> 0.045551805 | O24: =N24*L24 -> 0.027768381 | P24: 8000 | Q24: =P24*O24 -> 222.14704
A25: K-111 | B25: Centrifugal compressor | C25: Power, kW | D25: 929.59754 | E25: 580000 | F25: 20000 | G25: 0.6 | H25: =(E25+(F25*(D25^G25)))/1000000 -> 1.7878332 | J25: T-103 | K25: 1.372 | L25: =0.6096*2 -> 1.2192 | M25: =K25+0.0254 -> 1.3974 | N25: =PI()*(M25*M25-K25*K25)/4 -> 0.055247075 | O25: =N25*L25 -> 0.067357233 | P25: 8000 | Q25: =P25*O25 -> 538.85787
A26: K-112 | B26: Centrifugal compressor | C26: Power, kW | D26: 909.24838 | E26: 580000 | F26: 20000 | G26: 0.6 | H26: =(E26+(F26*(D26^G26)))/1000000 -> 1.7718992
A27: K-113 | B27: Centrifugal compressor | C27: Power, kW | D27: 532.87049 | E27: 580000 | F27: 20000 | G27: 0.6 | H27: =(E27+(F27*(D27^G27)))/1000000 -> 1.4449739
A28: K-114 | B28: Centrifugal compressor | C28: Power, kW | D28: 324.58093 | E28: 580000 | F28: 20000 | G28: 0.6 | H28: =(E28+(F28*(D28^G28)))/1000000 -> 1.222427
B29: Total | H29: =SUM(H14:H28) -> 21.325254
A30: Pumps
A31: P-100 | B31: Centrifugal pump | C31: Flow, litres/s | D31: =3.25533722751099*1000/3600 -> 0.90426034 | E31: 8000 | F31: 240 | G31: 0.9 | H31: =(E31+(F31*(D31^G31)))/1000000 -> 0.0082192176
A32: P-101 | B32: Centrifugal pump | C32: Flow, litres/s | D32: =35.7549190976969*1000/3600 -> 9.931922 | E32: 8000 | F32: 240 | G32: 0.9 | H32: =(E32+(F32*(D32^G32)))/1000000 -> 0.0098947033
A33: P-102 | B33: Centrifugal pump | C33: Flow, litres/s | D33: =50.579169062572*1000/3600 -> 14.049769 | E33: 8000 | F33: 240 | G33: 0.9 | H33: =(E33+(F33*(D33^G33)))/1000000 -> 0.010588889
B34: Total | H34: =SUM(H31:H33) -> 0.02870281
A35: Heat exchangers
A36: E-133 | B36: U tube HEX | C36: Area | D36: 18.909627 | E36: 28000 | F36: 54 | G36: 1.2 | H36: =(E36+(F36*(D36^G36)))/1000000 -> 0.029838287
A37: E-134 | B37: U tube HEX | C37: Area | D37: 218.60211 | E37: 28000 | F37: 54 | G37: 1.2 | H37: =(E37+(F37*(D37^G37)))/1000000 -> 0.062672008
A38: E-135 | B38: U tube HEX | C38: Area | D38: =1234.61009304443/2 -> 617.30505 | E38: 28000 | F38: 54 | G38: 1.2 | H38: =(E38+(F38*(D38^G38)))/1000000 -> 0.14850181
A39: E-135 | B39: U tube HEX | C39: Area | D39: =1234.61009304443/2 -> 617.30505 | E39: 28000 | F39: 54 | G39: 1.2 | H39: =(E39+(F39*(D39^G39)))/1000000 -> 0.14850181
A40: E-136 | B40: U tube HEX | C40: Area | D40: 90.881523 | E40: 28000 | F40: 54 | G40: 1.2 | H40: =(E40+(F40*(D40^G40)))/1000000 -> 0.040093847
A41: E-137 | B41: U tube HEX | C41: Area | D41: 17.246414 | E41: 28000 | F41: 54 | G41: 1.2 | H41: =(E41+(F41*(D41^G41)))/1000000 -> 0.02964601
A42: E-138 | B42: U tube HEX | C42: Area | D42: 204.35818 | E42: 28000 | F42: 54 | G42: 1.2 | H42: =(E42+(F42*(D42^G42)))/1000000 -> 0.05997895
A43: E-139 | B43: U tube HEX | C43: Area | D43: 0.063821011 | E43: 28000 | F43: 54 | G43: 1.2 | H43: =(E43+(F43*(D43^G43)))/1000000 -> 0.028001988
A44: E-140 | B44: U tube HEX | C44: Area | D44: 113.84361 | E44: 28000 | F44: 54 | G44: 1.2 | H44: =(E44+(F44*(D44^G44)))/1000000 -> 0.043847623
A45: E-141 | B45: U tube HEX | C45: Area | D45: =1825.13854356158/2 -> 912.56927 | E45: 28000 | F45: 54 | G45: 1.2 | H45: =(E45+(F45*(D45^G45)))/1000000 -> 0.22062505
A46: E-141 | B46: U tube HEX | C46: Area | D46: =1825.13854356158/2 -> 912.56927 | E46: 28000 | F46: 54 | G46: 1.2 | H46: =(E46+(F46*(D46^G46)))/1000000 -> 0.22062505
A47: E-142 | B47: U tube HEX | C47: Area | D47: 56.794539 | E47: 28000 | F47: 54 | G47: 1.2 | H47: =(E47+(F47*(D47^G47)))/1000000 -> 0.034879576
A48: E-143 | B48: U tube HEX | C48: Area | D48: 206.24577 | E48: 28000 | F48: 54 | G48: 1.2 | H48: =(E48+(F48*(D48^G48)))/1000000 -> 0.060333731
A49: E-144 | B49: U tube HEX | C49: Area | D49: 29.445712 | E49: 28000 | F49: 54 | G49: 1.2 | H49: =(E49+(F49*(D49^G49)))/1000000 -> 0.031127665
A50: E-145 | B50: U tube HEX | C50: Area | D50: 124.96725 | E50: 28000 | F50: 54 | G50: 1.2 | H50: =(E50+(F50*(D50^G50)))/1000000 -> 0.045723489
A51: E-146 | B51: U tube HEX | C51: Area | D51: 233.42707 | E51: 28000 | F51: 54 | G51: 1.2 | H51: =(E51+(F51*(D51^G51)))/1000000 -> 0.065512433
A52: E-147 | B52: U tube HEX | C52: Area | D52: 89.649502 | E52: 28000 | F52: 54 | G52: 1.2 | H52: =(E52+(F52*(D52^G52)))/1000000 -> 0.039897377
A53: E-148 | B53: U tube HEX | C53: Area | D53: 0.55461689 | E53: 28000 | F53: 54 | G53: 1.2 | H53: =(E53+(F53*(D53^G53)))/1000000 -> 0.028026619
A54: E-149 | B54: U tube HEX | C54: Area | D54: =1885.0926981447/2 -> 942.54635 | E54: 28000 | F54: 54 | G54: 1.2 | H54: =(E54+(F54*(D54^G54)))/1000000 -> 0.22824285
A55: E-149 | B55: U tube HEX | C55: Area | D55: =1885.0926981447/2 -> 942.54635 | E55: 28000 | F55: 54 | G55: 1.2 | H55: =(E55+(F55*(D55^G55)))/1000000 -> 0.22824285
A56: E-150 | B56: U tube HEX | C56: Area | D56: =1038.32431184317/2 -> 519.16216 | E56: 28000 | F56: 54 | G56: 1.2 | H56: =(E56+(F56*(D56^G56)))/1000000 -> 0.1258943
A57: E-150 | B57: U tube HEX | C57: Area | D57: =1038.32431184317/2 -> 519.16216 | E57: 28000 | F57: 54 | G57: 1.2 | H57: =(E57+(F57*(D57^G57)))/1000000 -> 0.1258943
A58: E-151 | B58: U tube HEX | C58: Area | D58: 35.265273 | E58: 28000 | F58: 54 | G58: 1.2 | H58: =(E58+(F58*(D58^G58)))/1000000 -> 0.031883385
A59: E-152 | B59: U tube HEX | C59: Area | D59: 154.07723 | E59: 28000 | F59: 54 | G59: 1.2 | H59: =(E59+(F59*(D59^G59)))/1000000 -> 0.05078662
A60: E-153 | B60: U tube HEX | C60: Area | D60: 129.93143 | E60: 28000 | F60: 54 | G60: 1.2 | H60: =(E60+(F60*(D60^G60)))/1000000 -> 0.046571664
A61: E-154 | B61: U tube HEX | C61: Area | D61: 339.41372 | E61: 28000 | F61: 54 | G61: 1.2 | H61: =(E61+(F61*(D61^G61)))/1000000 -> 0.08678534
A62: E-155 | B62: U tube HEX | C62: Area | D62: 73.45912 | E62: 28000 | F62: 54 | G62: 1.2 | H62: =(E62+(F62*(D62^G62)))/1000000 -> 0.037368038
A63: E-156 | B63: U tube HEX | C63: Area | D63: 0.39795013 | E63: 28000 | F63: 54 | G63: 1.2 | H63: =(E63+(F63*(D63^G63)))/1000000 -> 0.028017873
A64: E-157 | B64: U tube HEX | C64: Area | D64: 30.154409 | E64: 28000 | F64: 54 | G64: 1.2 | H64: =(E64+(F64*(D64^G64)))/1000000 -> 0.031218213
A65: E-158 | B65: U tube HEX | C65: Area | D65: 68.37364 | E65: 28000 | F65: 54 | G65: 1.2 | H65: =(E65+(F65*(D65^G65)))/1000000 -> 0.036595283
A66: E-159 | B66: U tube HEX | C66: Area | D66: 762.7243 | E66: 28000 | F66: 54 | G66: 1.2 | H66: =(E66+(F66*(D66^G66)))/1000000 -> 0.18332267
A67: E-160 | B67: U tube HEX | C67: Area | D67: 4.4077803 | E67: 28000 | F67: 54 | G67: 1.2 | H67: =(E67+(F67*(D67^G67)))/1000000 -> 0.028320227
A68: E-161 | B68: U tube HEX | C68: Area | D68: 0.12942599 | E68: 28000 | F68: 54 | G68: 1.2 | H68: =(E68+(F68*(D68^G68)))/1000000 -> 0.028004643
A69: E-162 | B69: U tube HEX | C69: Area | D69: 43.824976 | E69: 28000 | F69: 54 | G69: 1.2 | H69: =(E69+(F69*(D69^G69)))/1000000 -> 0.033040339
... A79: E-172 | B79: U tube HEX | C79: Area | D79: 5.9538785 | E79: 28000 | F79: 54 | G79: 1.2 | H79: =(E79+(F79*(D79^G79)))/1000000 -> 0.028459361
A80: E-173 | B80: U tube HEX | C80: Area | D80: =1415.80818491959/2 -> 707.90409 | E80: 28000 | F80: 54 | G80: 1.2 | H80: =(E80+(F80*(D80^G80)))/1000000 -> 0.17002443
A81: E-173 | B81: U tube HEX | C81: Area | D81: =1415.80818491959/2 -> 707.90409 | E81: 28000 | F81: 54 | G81: 1.2 | H81: =(E81+(F81*(D81^G81)))/1000000 -> 0.17002443
A82: E-174 | B82: U tube HEX | C82: Area | D82: 118.84488 | E82: 28000 | F82: 54 | G82: 1.2 | H82: =(E82+(F82*(D82^G82)))/1000000 -> 0.044686695
A83: E-175 | B83: U tube HEX | C83: Area | D83: 144.80962 | E83: 28000 | F83: 54 | G83: 1.2 | H83: =(E83+(F83*(D83^G83)))/1000000 -> 0.049151962
A84: E-176 | B84: U tube HEX | C84: Area | D84: 30.031706 | E84: 28000 | F84: 54 | G84: 1.2 | H84: =(E84+(F84*(D84^G84)))/1000000 -> 0.031202505
A85: E-177 | B85: U tube HEX | C85: Area | D85: 1.1889251 | E85: 28000 | F85: 54 | G85: 1.2 | H85: =(E85+(F85*(D85^G85)))/1000000 -> 0.028066463
A86: E-178 | B86: U tube HEX | C86: Area | D86: 19.267002 | E86: 28000 | F86: 54 | G86: 1.2 | H86: =(E86+(F86*(D86^G86)))/1000000 -> 0.029880056
A87: E-179 | B87: U tube HEX | C87: Area | D87: 105.99895 | E87: 28000 | F87: 54 | G87: 1.2 | H87: =(E87+(F87*(D87^G87)))/1000000 -> 0.042546404
A88: E-180 | B88: U tube HEX | C88: Area | D88: 283.97327 | E88: 28000 | F88: 54 | G88: 1.2 | H88: =(E88+(F88*(D88^G88)))/1000000 -> 0.075459889
A89: E-181 | B89: U tube HEX | C89: Area | D89: 194.39642 | E89: 28000 | F89: 54 | G89: 1.2 | H89: =(E89+(F89*(D89^G89)))/1000000 -> 0.058117553
A90: E-182 | B90: U tube HEX | C90: Area | D90: 408.74872 | E90: 28000 | F90: 54 | G90: 1.2 | H90: =(E90+(F90*(D90^G90)))/1000000 -> 0.10147531
A91: E-183 | B91: U tube HEX | C91: Area | D91: 763.36242 | E91: 28000 | F91: 54 | G91: 1.2 | H91: =(E91+(F91*(D91^G91)))/1000000 -> 0.18347862
A92: E-184 | B92: U tube HEX | C92: Area | D92: 246.50685 | E92: 28000 | F92: 54 | G92: 1.2 | H92: =(E92+(F92*(D92^G92)))/1000000 -> 0.068048711
A93: E-185 | B93: U tube HEX | C93: Area | D93: 403.60386 | E93: 28000 | F93: 54 | G93: 1.2 | H93: =(E93+(F93*(D93^G93)))/1000000 -> 0.10036693
... A97: E-189 | B97: U tube HEX | C97: Area | D97: 67.417598 | E97: 28000 | F97: 54 | G97: 1.2 | H97: =(E97+(F97*(D97^G97)))/1000000 -> 0.036451264
B98: Total | H98: =SUM(H36:H97) -> 4.5325366
A99: Reactors
A100: POX | B100: Pressure vessel | C100: Shell mass, kg | D100: =Q13 -> 2616.2888 | E100: 17400 | F100: 79 | G100: 0.85 | H100: =(E100+(F100*(D100^G100)))/1000000 -> 0.080883363
A101: WGS reactor | B101: Furnace | C101: Duty, MW | D101: =36770/1000 -> 36.77 | E101: 80000 | F101: 109000 | G101: 0.8 | H101: =(E101+(F101*(D101^G101)))/1000000 -> 2.0290429
A102: Hydroformylation | B102: Furnace | C102: Duty, MW | D102: =40870/1000 -> 40.87 | E102: 80000 | F102: 109000 | G102: 0.8 | H102: =(E102+(F102*(D102^G102)))/1000000 -> 2.2010466
A103: Methanation | B103: Furnace | C103: Duty, MW | D103: =560.9/1000 -> 0.5609 | E103: 80000 | F103: 109000 | G103: 0.8 | H103: =(E103+(F103*(D103^G103)))/1000000 -> 0.1486333
A104: Hydrogenation | B104: Furnace | C104: Duty, MW | D104: =17660/1000 -> 17.66 | E104: 80000 | F104: 109000 | G104: 0.8 | H104: =(E104+(F104*(D104^G104)))/1000000 -> 1.1639745
B105: Total | H105: =SUM(H100:H104) -> 5.6235806
A106: Flash separators
A107: V-100 | B107: Pressure vessel | C107: Shell mass, kg | D107: =Q14 -> 2616.2888 | E107: 17400 | F107: 79 | G107: 0.85 | H107: =(E107+(F107*(D107^G107)))/1000000 -> 0.080883363
A108: V-101 | B108: Pressure vessel | C108: Shell mass, kg | D108: =Q15 -> 665.96442 | E108: 17400 | F108: 79 | G108: 0.85 | H108: =(E108+(F108*(D108^G108)))/1000000 -> 0.037240859
A109: V-102 | B109: Pressure vessel | C109: Shell mass, kg | D109: =Q16 -> 11487.886 | E109: 17400 | F109: 79 | G109: 0.85 | H109: =(E109+(F109*(D109^G109)))/1000000 -> 0.24067043
A110: V-103 | B110: Pressure vessel | C110: Shell mass, kg | D110: =Q17 -> 2021.6777 | E110: 17400 | F110: 79 | G110: 0.85 | H110: =(E110+(F110*(D110^G110)))/1000000 -> 0.068389673
A111: V-104 | B111: Pressure vessel | C111: Shell mass, kg | D111: =Q18 -> 169.88888 | E111: 17400 | F111: 79 | G111: 0.85 | H111: =(E111+(F111*(D111^G111)))/1000000 -> 0.023612513
A112: V-105 | B112: Pressure vessel | C112: Shell mass, kg | D112: =Q19 -> 3333.2199 | E112: 17400 | F112: 79 | G112: 0.85 | H112: =(E112+(F112*(D112^G112)))/1000000 -> 0.095394048
A113: V-106 | B113: Pressure vessel | C113: Shell mass, kg | D113: =Q20 -> 659.47776 | E113: 17400 | F113: 79 | G113: 0.85 | H113: =(E113+(F113*(D113^G113)))/1000000 -> 0.037076471
A114: V-107 | B114: Pressure vessel | C114: Shell mass, kg | D114: =Q21 -> 3333.2199 | E114: 17400 | F114: 79 | G114: 0.85 | H114: =(E114+(F114*(D114^G114)))/1000000 -> 0.095394048
...

Sheet Production costs
A4: Description | B4: Assumption | C4: M$/year
A5: Labor Costs
A6: Operating labor | B6: 9 shift positions, 9 operators/shift | C6: =50000*9*9/1000000 -> 4.05
A7: Supervision | B7: 25% of operating Labor | C7: =0.25*C6 -> 1.0125
A8: Direct overhead | B8: 45% of labor and supervision | C8: =0.45*(C6+C7) -> 2.278125
C9: =SUM(C6:C8) -> 7.340625
A10: Maintanance Costs
A11: Maintanance | B11: 3% of the installed capital cost | C11: =0.03*CAPEX!B137 -> 5.4790808
C12: =C11 -> 5.4790808
A13: Overhead Expenses
A14: Plant overhead | B14: 65% of labor and maintanace | C14: =0.65*(C6+C7+C8+C11) -> 8.3328087
A15: Tax & Insurance | B15: 2% of installed cost and offsites | C15: =0.02*(CAPEX!B137+CAPEX!B138) -> 4.7485367
C16: =SUM(C14:C15) -> 13.081345
A17: Interest
A18: Interest on debit | B18: 6% of working capital | C18: =0.06*CAPEX!B142 -> 2.9915781
C19: =C18 -> 2.9915781
A20: Total fixed production costs | C20: =C9+C12+C16+C19 -> 28.892629

Sheet Catalyst costs
A1: Propanol produced | D1: 56724.188 | E1: kg/hr
A4: Unit operation | B4: Catalyst used | C4: kg/hr | D4: $/kg | E4: $/hr | F4: M$/year
A5: Hydroformylation | B5: Rh/PPh3 | C5: 0.0081 | D5: 286000 | E5: =C5*D5 -> 2316.6 | F5: =E5/10^6*8000 -> 18.5328 | G5: Sigma Aldrich: https://www.sigmaaldrich.com/US/en/product/aldrich/225665

Sheet OPEX
B3: Material | C3: Unit | D3: Quantity | E3: Price ($/unit) | F3: Total cost | G3: 2022 costs | H3: Reference
B4: Raw material costs | K4: $/cu. ft | L4: $/MJ | M4: $/kg
B5: Natural gas | C5: ton/hr | D5: =17147.7393199539/1000 -> 17.147739 | E5: 524 | F5: =E5*D5 -> 8985.4154 | G5: =F5*C30/C29 -> 9301.4039 | H5: Europa 2021 | J5: Natural gas | K5: =13.4/1000 -> 0.0134 | L5: =K5/1.06 -> 0.012641509 | M5: =L5*55 -> 0.69528302
B6: Oxygen | C6: ton/hr | D6: =23942.63872/1000 -> 23.942639 | E6: 123.25 | F6: =E6*D6 -> 2950.9302 | G6: =F6*C30/C27 -> 3931.9641 | H6: Lin 2018 (pg. 4)
B7: Ethylene | C7: ton/hr | D7: =26751.3222258341/1000 -> 26.751322 | E7: 1293 | F7: =E7*D7 -> 34589.46 | G7: =F7*C30/C28 -> 45754.88 | H7: Iasonas 2020
B8: Hydrogen | C8: ton/hr | D8: 0 | E8: 2090 | F8: =E8*D8 -> 0 | G8: =F8*C30/C28 -> 0 | H8: Iasonas 2020
B9: Total | G9: =SUM(G5:G8) -> 58988.248
B10: Utility costs
B11: Cooling water | C11: m3/hr | D11: =10758125.8574591/1000 -> 10758.126 | E11: =3.6/100 -> 0.036 | F11: =E11*D11 -> 387.29253 | G11: =F11*C30/C28 -> 512.30992 | H11: Iasonas 2020
B12: Electricity | C12: MWh | D12: =10614.1476562558/1000 -> 10.614148 | E12: 69.6 | F12: =E12*D12 -> 738.74468 | G12: =F12*C30/C28 -> 977.21024 | H12: Iasonas 2020
B13: Total | G13: =SUM(G11:G12) -> 1489.5202
B14: Additional costs (purge,etc)
B15: CO2 capture and storage | C15: ton/hr | D15: =6329.92841251293/1000 -> 6.3299284 | E15: 15 | F15: =E15*D15 -> 94.948926 | G15: =F15*C$30/C$26 -> 132.60507 | H15: Dooley 2008 (pg. 5)
B16: Wastewater treatment | C16: m3/hr | D16: =4935.31844125278/1000 -> 4.9353184 | E16: 1.6 | F16: =E16*D16 -> 7.8965095 | G16: =F16*C30/C28 -> 10.44549 | H16: Iasonas 2020
B17: Flue gas emissions | C17: ton/hr | D17: =5.44920083829079/1000 -> 0.0054492008 | E17: 200 | F17: =E17*D17 -> 1.0898402 | G17: =F17*C30/C27 -> 1.4521565 | H17: Turton 2018 (pg. 246)
B18: Total | G18: =SUM(G15:G17) -> 144.50272
B19: Products sold
B20: Steam | C20: ton/hr | D20: =-83396.4629121811/1000 -> -83.396463 | E20: 15.6 | F20: =E20*D20 -> -1300.9848 | G20: =F20*C30/C28 -> -1720.9406 | H20: Iasonas 2020
B21: Total | G21: =SUM(G20) -> -1720.9406
B22: Catalyst costs | C22: M$/year | G22: =SUM('Catalyst costs'!F5) -> 18.5328 | H22: Refer catalyst costs sheet
B23: Total OPEX | C23: M$/year | G23: =(G9+G13+G18+G21)*8000/1000000+G$22 -> 489.74344
B25: Reference Data
B26: CEPCI 2008 | C26: 575.4
B27: CEPCI 2018 | C27: 603.1
B28: CEPCI 2019 | C28: 607.5
B29: CEPCI 2021 | C29: 776.3
B30: CEPCI 2022 | C30: 803.6

Sheet Summary
B3: Purchased equipment cost 2022 (M$/year) | C3: =SUM(CAPEX!B136) -> 48.833162 | E3: CAPEX summary | J3: CAPEX short summary
B4: Installed capital cost | C4: =SUM(CAPEX!B137) -> 182.63603 | E4: Unit operation | F4: Contribution 2010 | G4: Contribution 2022 | H4: CAPEX [M$/year] | J4: Unit operation | K4: CAPEX [M$/year]
B5: Offsites (OS) | C5: =SUM(CAPEX!B138) -> 54.790808 | E5: Compressors | F5: =CAPEX!H29 -> 21.325254 | G5: =F5*CAPEX!$B$135/CAPEX!$B$134 -> 32.157955 | H5: =(G5*CAPEX!$C$141+Summary!G5*CAPEX!$C$141*0.15)*CAPEX!$B$146 -> 32.095145 | J5: Compressors | K5: =H5 -> 32.095145
B6: Design and engineering (D&E) | C6: =SUM(CAPEX!B139) -> 71.22805 | E6: Pumps | F6: =CAPEX!H34 -> 0.02870281 | G6: =F6*CAPEX!$B$135/CAPEX!$B$134 -> 0.043283127 | H6: =(G6*CAPEX!$C$141+Summary!G6*CAPEX!$C$141*0.15)*CAPEX!$B$146 -> 0.043198587 | J6: Pumps | K6: =H6 -> 0.043198587
B7: Contingency (X) | C7: =SUM(CAPEX!B140) -> 23.742683 | E7: Heat exchangers | F7: =CAPEX!H98 -> 4.5325366 | G7: =F7*CAPEX!$B$135/CAPEX!$B$134 -> 6.834953 | H7: =(G7*CAPEX!$C$141+Summary!G7*CAPEX!$C$141*0.15)*CAPEX!$B$146 -> 6.821603 | J7: Heat exchangers | K7: =H7 -> 6.821603
B8: Fixed capital investment | C8: =SUM(CAPEX!B141) -> 332.39757 | E8: Reactors | F8: =CAPEX!H105 -> 5.6235806 | G8: =F8*CAPEX!$B$135/CAPEX!$B$134 -> 8.4802203 | H8: =(G8*CAPEX!$C$141+Summary!G8*CAPEX!$C$141*0.15)*CAPEX!$B$146 -> 8.4636569 | J8: Reactors | K8: =H8 -> 8.4636569
B9: Working capital | C9: =SUM(CAPEX!B142) -> 49.859635 | E9: Flash separators | F9: =CAPEX!H115 -> 0.6786614 | G9: =F9*CAPEX!$B$135/CAPEX!$B$134 -> 1.0234046 | H9: =(G9*CAPEX!$C$141+Summary!G9*CAPEX!$C$141*0.15)*CAPEX!$B$146 -> 1.0214057 | J9: Flash separators | K9: =H9 -> 1.0214057
B10: Total investment | C10: =SUM(CAPEX!B143) -> 382.2572 | E10: Columns | F10: =CAPEX!H119+CAPEX!H123+CAPEX!H127+CAPEX!H131 -> 0.19452956 | G10: =F10*CAPEX!$B$135/CAPEX!$B$134 -> 0.29334576 | H10: =(G10*CAPEX!$C$141+Summary!G10*CAPEX!$C$141*0.15)*CAPEX!$B$146 -> 0.2927728 | J10: Columns | K10: =H10 -> 0.2927728
B11: Labor costs | C11: =SUM('Production costs'!C9) -> 7.340625 | E11: Total | F11: =SUM(F5:F10) -> 32.383265 | G11: =SUM(G5:G10) -> 48.833162 | H11: =SUM(H5:H10) -> 48.737782 | J11: Total | K11: =SUM(K5:K10) -> 48.737782
B12: Maintanance costs | C12: =SUM('Production costs'!C12) -> 5.4790808
B13: Overhead expenses | C13: =SUM('Production costs'!C16) -> 13.081345 | E13: Production costs summary | J13: Production costs short summary
B14: Interest | C14: =SUM('Production costs'!C19) -> 2.9915781 | E14: Category | F14: M$/year | J14: Category | K14: M$/year
B15: Project lifetime | C15: =SUM(CAPEX!B144) -> 25 | E15: Operating labor | F15: ='Production costs'!C6 -> 4.05 | J15: Labor | K15: =F15+F16+F17 -> 7.340625
B16: Interest rate | C16: =SUM(CAPEX!B145) -> 0.12 | E16: Supervision | F16: ='Production costs'!C7 -> 1.0125 | J16: Maintanance | K16: =F18 -> 5.4790808
B17: ACCR | C17: =SUM(CAPEX!B146) -> 0.12749997 | E17: Direct overhead | F17: ='Production costs'!C8 -> 2.278125 | J17: Overhead | K17: =F19+F20 -> 13.081345
B18: CAPEX (M$/year) | C18: =SUM(CAPEX!B148) -> 48.737782 | E18: Maintanance | F18: ='Production costs'!C11 -> 5.4790808 | J18: Interest | K18: =F21 -> 2.9915781
B19: Fixed production costs (M$/year) | C19: ='Production costs'!C20 -> 28.892629 | E19: Plant overhead | F19: ='Production costs'!C14 -> 8.3328087 | J19: Total | K19: =SUM(K15:K18) -> 28.892629
B20: OPEX (M$/year) | C20: =OPEX!G23 -> 489.74344 | E20: Tax & Insurance | F20: ='Production costs'!C15 -> 4.7485367
B21: Total expenses (M$/year) | C21: =($C$18+$C$19+C20) -> 567.37385 | E21: Interest on debit | F21: ='Production costs'!C18 -> 2.9915781
B22: Total expenses ($/hr) | C22: =(C21)*1000000/8000 -> 70921.732 | E22: Total | F22: =SUM(F15:F21) -> 28.892629
B23: Total propanol produced (kg/hr) | C23: 56724.823
B24: Cost of propanol per kg | C24: =C22/C23 -> 1.2502768 | E24: OPEX short summary
B25: Cost of propanol per ton | C25: =C24*1000 -> 1250.2768 | E25: Category | F25: M$/year
E26: Natural gas | F26: =OPEX!G5*8000/10^6 -> 74.411231
E27: Oxygen | F27: =OPEX!G6*8000/10^6 -> 31.455713
E28: Ethylene | F28: =OPEX!G7*8000/10^6 -> 366.03904
E29: Hydrogen | F29: =OPEX!G8*8000/10^6 -> 0
E30: Cooling water | F30: =OPEX!G11*8000/10^6 -> 4.0984794
E31: Electricity | F31: =OPEX!G12*8000/10^6 -> 7.8176819
E32: CO2 capture and storage | F32: =OPEX!G15*8000/10^6 -> 1.0608406
E33: Wastewater treatment | F33: =OPEX!G16*8000/10^6 -> 0.083563918
E34: Flue gas emissions | F34: =OPEX!G17*8000/10^6 -> 0.011617252
E35: Steam | F35: =OPEX!G20*8000/10^6 -> -13.767525
E36: Catalyst | F36: =OPEX!G22 -> 18.5328
E37: Total | F37: =SUM(F26:F36) -> 489.74344
E39: Overall
E40: Category | F40: Contribution $/t | G40: Required (unit/hr) | H40: Unit
E41: Natural gas | F41: =F26*10^9/8000/$C$23 -> 163.97414 | G41: =OPEX!D5 -> 17.147739 | H41: ton/hr
E42: Carbon dioxide | F42: 0 | G42: 0 | H42: ton/hr
E43: Biogas | F43: 0 | G43: 0 | H43: ton/hr
E44: Oxygen | F44: =F27*10^9/8000/$C$23 -> 69.316462 | G44: =OPEX!D6 -> 23.942639 | H44: ton/hr
E45: Hydrogen | F45: =F29*10^9/8000/$C$23 -> 0 | G45: =OPEX!D8 -> 0 | H45: ton/hr
E46: Ethylene | F46: =F28*10^9/8000/$C$23 -> 806.61124 | G46: =OPEX!D7 -> 26.751322 | H46: ton/hr
E47: Cooling water | F47: =F30*10^9/8000/$C$23 -> 9.0314944 | G47: =OPEX!D11 -> 10758.126 | H47: m3/hr
E48: Electricity | F48: =F31*10^9/8000/$C$23 -> 17.227206 | G48: =OPEX!D12 -> 10.614148 | H48: MWh
E49: Fired heat - natural gas | F49: 0 | G49: 0 | H49: ton/hr
E50: Carbon dioxide storage | F50: =F32*10^9/8000/$C$23 -> 2.3376903 | G50: =OPEX!D15 -> 6.3299284 | H50: ton/hr
E51: Wastewater treatment | F51: =F33*10^9/8000/$C$23 -> 0.18414319 | G51: =OPEX!D16 -> 4.9353184 | H51: m3/hr
E52: Flue gas emissions | F52: =F34*10^9/8000/$C$23 -> 0.025600017 | G52: =OPEX!D17 -> 0.0054492008 | H52: ton/hr
E53: Steam | F53: =F35*10^9/8000/$C$23 -> -30.338404 | G53: =OPEX!D20 -> -83.396463 | H53: ton/hr
E54: Catalyst | F54: =F36*10^9/8000/$C$23 -> 40.839263 | G54: 0 | H54: -
E55: Fixed Costs | F55: =K19*10^9/8000/$C$23 -> 63.668399 | G55: 0 | H55: -
E56: CAPEX | F56: =H11*10^9/8000/$C$23 -> 107.39959 | G56: 0 | H56: -
E57: Total | F57: =SUM(F41:F56) -> 1250.2768
